future_tstrings/__init__.py
future_tstrings/__main__.py
future_tstrings/_autoinstall.py
future_tstrings/importer.py
future_tstrings/main.py
future_tstrings/py.typed
future_tstrings/templatelib.py
future_tstrings/parser/__init__.py
future_tstrings/parser/parse_grammar.py
future_tstrings/parser/xgrammar313.txt
future_tstrings/parser/compiler/__init__.py
future_tstrings/parser/compiler/ast.py
future_tstrings/parser/compiler/ast_apply_offset.py
future_tstrings/parser/compiler/compile.py
future_tstrings/parser/compiler/positions.py
future_tstrings/parser/tokenizer/__init__.py
future_tstrings/parser/tokenizer/_tokens_re.py
future_tstrings/parser/tokenizer/_tokens_util.py
future_tstrings/parser/tokenizer/tokenize.py
hatch_autorun_future_tstrings.pth
future_tstrings-1.0.0.dist-info/METADATA
future_tstrings-1.0.0.dist-info/WHEEL
future_tstrings-1.0.0.dist-info/entry_points.txt
future_tstrings-1.0.0.dist-info/licenses/LICENSE
future_tstrings-1.0.0.dist-info/RECORD
