Metadata-Version: 2.4
Name: future-tstrings
Version: 1.0.0
Summary: Backport of tstrings to python <3.14, and full-syntax fstrings to python <3.12
Author-email: Marckie Zeender <mkzeender@gmail.com>
License-File: LICENSE
Requires-Python: >=3.8
Requires-Dist: parso==0.8.4; python_version < '3.14'
